pyframe_eval/__init__.py
pyframe_eval/_pyframe_eval.cpython-311-darwin.so
pyframe_eval-0.0.3.2.dist-info/RECORD
pyframe_eval-0.0.3.2.dist-info/LICENSE
pyframe_eval-0.0.3.2.dist-info/WHEEL
pyframe_eval-0.0.3.2.dist-info/top_level.txt
pyframe_eval-0.0.3.2.dist-info/METADATA
